Metadata-Version: 1.0
Name: slackborg
Version: 0.0.2
Summary: A simple semi-conversational, multi-step workflow slack bot framework.
Home-page: https://github.com/josefdlange/slackborg
Author: Josef Lange
Author-email: josef.d.lange@me.com
License: MIT
Platform: UNKNOWN
